{"data_mtime": 1656157773, "dep_lines": [1, 2, 3, 4, 5, 6, 7, 1, 1, 1], "dep_prios": [10, 10, 10, 5, 5, 5, 5, 5, 30, 30], "dependencies": ["enum", "socket", "sys", "_typeshed", "collections.abc", "typing", "typing_extensions", "builtins", "_socket", "abc"], "hash": "b8ce77d004d4bdaf1727018c298195bc67758c138c56f455c12a080e02b2191c", "id": "ssl", "ignore_all": true, "interface_hash": "4e3b55035885cb2e27541e06b492704754e1b4cf74edd70cea87f9037f6b1133", "mtime": 1654111324, "options": {"allow_redefinition": false, "allow_untyped_globals": false, "always_false": [], "always_true": [], "bazel": false, "check_untyped_defs": true, "disallow_any_decorated": false, "disallow_any_explicit": false, "disallow_any_expr": false, "disallow_any_generics": true, "disallow_any_unimported": false, "disallow_incomplete_defs": true, "disallow_subclassing_any": true, "disallow_untyped_calls": true, "disallow_untyped_decorators": true, "disallow_untyped_defs": true, "follow_imports": "normal", "follow_imports_for_stubs": false, "ignore_errors": false, "ignore_missing_imports": false, "implicit_reexport": false, "local_partial_types": false, "mypyc": false, "no_implicit_optional": true, "platform": "win32", "plugins": [], "show_none_errors": true, "strict_concatenate": true, "strict_equality": true, "strict_optional": true, "strict_optional_whitelist": null, "warn_no_return": true, "warn_return_any": true, "warn_unreachable": false, "warn_unused_ignores": true}, "path": "C:\\Users\\alex\\AppData\\Local\\pypoetry\\Cache\\virtualenvs\\ancv-9X3ziGwo-py3.10\\lib\\site-packages\\mypy\\typeshed\\stdlib\\ssl.pyi", "plugin_data": null, "size": 19294, "suppressed": [], "version_id": "0.960"}